<NotepadPlus>
    <UserLang name="HLSL for ShaderHacker" ext="" udlVersion="2.1">
        <Settings>
            <Global caseIgnored="no" allowFoldOfComments="yes" foldCompact="no" forcePureLC="0" decimalSeparator="0" />
            <Prefix Keywords1="no" Keywords2="no" Keywords3="no" Keywords4="no" Keywords5="no" Keywords6="no" Keywords7="no" Keywords8="no" />
        </Settings>
        <KeywordLists>
            <Keywords name="Comments">00// 01 02 03/* 04*/</Keywords>
            <Keywords name="Numbers, prefix1"></Keywords>
            <Keywords name="Numbers, prefix2"></Keywords>
            <Keywords name="Numbers, extras1"></Keywords>
            <Keywords name="Numbers, extras2"></Keywords>
            <Keywords name="Numbers, suffix1"></Keywords>
            <Keywords name="Numbers, suffix2"></Keywords>
            <Keywords name="Numbers, range"></Keywords>
            <Keywords name="Operators1">. &lt; &gt; = ( ) { } , ; == * + - / % [ ]</Keywords>
            <Keywords name="Operators2"></Keywords>
            <Keywords name="Folders in code1, open"></Keywords>
            <Keywords name="Folders in code1, middle"></Keywords>
            <Keywords name="Folders in code1, close"></Keywords>
            <Keywords name="Folders in code2, open"></Keywords>
            <Keywords name="Folders in code2, middle"></Keywords>
            <Keywords name="Folders in code2, close"></Keywords>
            <Keywords name="Folders in comment, open"></Keywords>
            <Keywords name="Folders in comment, middle"></Keywords>
            <Keywords name="Folders in comment, close"></Keywords>
            <Keywords name="Keywords1">float&#x000D;&#x000A;float4&#x000D;&#x000A;float3&#x000D;&#x000A;int4&#x000D;&#x000A;uint4&#x000D;&#x000A;dot&#x000D;&#x000A;Load&#x000D;&#x000A;return&#x000D;&#x000A;#define&#x000D;&#x000A;&#x000D;&#x000A;</Keywords>
            <Keywords name="Keywords2">r0&#x000D;&#x000A;r1&#x000D;&#x000A;r2&#x000D;&#x000A;r3&#x000D;&#x000A;r4&#x000D;&#x000A;r5&#x000D;&#x000A;r6&#x000D;&#x000A;r7&#x000D;&#x000A;r8&#x000D;&#x000A;r9&#x000D;&#x000A;r10&#x000D;&#x000A;v0&#x000D;&#x000A;v1&#x000D;&#x000A;v2&#x000D;&#x000A;v3&#x000D;&#x000A;v4&#x000D;&#x000A;v5&#x000D;&#x000A;v6&#x000D;&#x000A;v7&#x000D;&#x000A;v8&#x000D;&#x000A;v9&#x000D;&#x000A;v10&#x000D;&#x000A;o0&#x000D;&#x000A;o1&#x000D;&#x000A;o2&#x000D;&#x000A;cb0&#x000D;&#x000A;cb1&#x000D;&#x000A;cb2&#x000D;&#x000A;cb3&#x000D;&#x000A;cb4&#x000D;&#x000A;cb5&#x000D;&#x000A;cb6&#x000D;&#x000A;cb7&#x000D;&#x000A;cb8&#x000D;&#x000A;cb9&#x000D;&#x000A;cb10</Keywords>
            <Keywords name="Keywords3">t0&#x000D;&#x000A;t1&#x000D;&#x000A;t2&#x000D;&#x000A;t3&#x000D;&#x000A;t4&#x000D;&#x000A;t5&#x000D;&#x000A;t6&#x000D;&#x000A;t7&#x000D;&#x000A;t8&#x000D;&#x000A;t9&#x000D;&#x000A;t10</Keywords>
            <Keywords name="Keywords4">VGCOUNT&#x000D;&#x000A;FRAME&#x000D;&#x000A;VertexGroupCount&#x000D;&#x000A;TotalFrameNumber</Keywords>
            <Keywords name="Keywords5">dcl_constantbuffer&#x000D;&#x000A;dcl_globalFlags&#x000D;&#x000A;dcl_resource_raw&#x000D;&#x000A;dcl_resource_structured&#x000D;&#x000A;dcl_uav_raw&#x000D;&#x000A;dcl_input&#x000D;&#x000A;dcl_temps&#x000D;&#x000A;dcl_thread_group&#x000D;&#x000A;uge&#x000D;&#x000A;if_nz&#x000D;&#x000A;ret&#x000D;&#x000A;endif&#x000D;&#x000A;imul&#x000D;&#x000A;ld_raw_indexable&#x000D;&#x000A;raw_buffer&#x000D;&#x000A;ld_structured_indexable&#x000D;&#x000A;structured_buffer&#x000D;&#x000A;stride&#x000D;&#x000A;mixed&#x000D;&#x000A;imad&#x000D;&#x000A;ishl&#x000D;&#x000A;mov&#x000D;&#x000A;mul&#x000D;&#x000A;mad&#x000D;&#x000A;dp4&#x000D;&#x000A;dp3&#x000D;&#x000A;</Keywords>
            <Keywords name="Keywords6">store_raw</Keywords>
            <Keywords name="Keywords7"></Keywords>
            <Keywords name="Keywords8"></Keywords>
            <Keywords name="Delimiters">00 01 02 03 04 05 06 07 08 09 10 11 12 13 14 15 16 17 18 19 20 21 22 23</Keywords>
        </KeywordLists>
        <Styles>
            <WordsStyle name="DEFAULT" fgColor="00FF40" bgColor="000000" colorStyle="1" fontName="Nirmala UI" fontStyle="0" nesting="0" />
            <WordsStyle name="COMMENTS" fgColor="FF8040" bgColor="000000" colorStyle="1" fontStyle="7" nesting="0" />
            <WordsStyle name="LINE COMMENTS" fgColor="FF8000" bgColor="000000" colorStyle="1" fontStyle="1" nesting="0" />
            <WordsStyle name="NUMBERS" fgColor="FFFF80" bgColor="000000" colorStyle="1" fontStyle="1" nesting="0" />
            <WordsStyle name="KEYWORDS1" fgColor="0080FF" bgColor="FFFFFF" colorStyle="1" fontStyle="3" nesting="0" />
            <WordsStyle name="KEYWORDS2" fgColor="FF80C0" bgColor="000000" colorStyle="1" fontStyle="1" nesting="0" />
            <WordsStyle name="KEYWORDS3" fgColor="8080FF" bgColor="000000" colorStyle="1" fontStyle="1" nesting="0" />
            <WordsStyle name="KEYWORDS4" fgColor="00FFFF" bgColor="000000" colorStyle="1" fontStyle="1" nesting="0" />
            <WordsStyle name="KEYWORDS5" fgColor="0080FF" bgColor="FFFFFF" colorStyle="1" fontStyle="1" nesting="0" />
            <WordsStyle name="KEYWORDS6" fgColor="FF0000" bgColor="FFFFFF" colorStyle="1" fontStyle="0" nesting="0" />
            <WordsStyle name="KEYWORDS7" fgColor="000000" bgColor="FFFFFF" fontStyle="0" nesting="0" />
            <WordsStyle name="KEYWORDS8" fgColor="000000" bgColor="FFFFFF" fontStyle="0" nesting="0" />
            <WordsStyle name="OPERATORS" fgColor="FF0080" bgColor="000000" colorStyle="1" fontStyle="0" nesting="0" />
            <WordsStyle name="FOLDER IN CODE1" fgColor="000000" bgColor="FFFFFF" fontStyle="0" nesting="0" />
            <WordsStyle name="FOLDER IN CODE2" fgColor="000000" bgColor="FFFFFF" fontStyle="0" nesting="0" />
            <WordsStyle name="FOLDER IN COMMENT" fgColor="000000" bgColor="FFFFFF" fontStyle="0" nesting="0" />
            <WordsStyle name="DELIMITERS1" fgColor="000000" bgColor="FFFFFF" fontStyle="0" nesting="0" />
            <WordsStyle name="DELIMITERS2" fgColor="000000" bgColor="FFFFFF" fontStyle="0" nesting="0" />
            <WordsStyle name="DELIMITERS3" fgColor="000000" bgColor="FFFFFF" fontStyle="0" nesting="0" />
            <WordsStyle name="DELIMITERS4" fgColor="000000" bgColor="FFFFFF" fontStyle="0" nesting="0" />
            <WordsStyle name="DELIMITERS5" fgColor="000000" bgColor="FFFFFF" fontStyle="0" nesting="0" />
            <WordsStyle name="DELIMITERS6" fgColor="000000" bgColor="FFFFFF" fontStyle="0" nesting="0" />
            <WordsStyle name="DELIMITERS7" fgColor="000000" bgColor="FFFFFF" fontStyle="0" nesting="0" />
            <WordsStyle name="DELIMITERS8" fgColor="000000" bgColor="FFFFFF" fontStyle="0" nesting="0" />
        </Styles>
    </UserLang>
</NotepadPlus>
